AUTHORS
README.rst
setup.cfg
setup.py
krules_subjects_storage_mongodb.egg-info/PKG-INFO
krules_subjects_storage_mongodb.egg-info/SOURCES.txt
krules_subjects_storage_mongodb.egg-info/dependency_links.txt
krules_subjects_storage_mongodb.egg-info/requires.txt
krules_subjects_storage_mongodb.egg-info/top_level.txt
mongodb_subjects_storage/__init__.py
mongodb_subjects_storage/storage_impl.py
mongodb_subjects_storage/test_storage.py
mongodb_subjects_storage/test_storage_atomic_ops.py
mongodb_subjects_storage/test_storage_no_atomic_ops.py